setup.py
gym_wrappers/__init__.py
gym_wrappers.egg-info/PKG-INFO
gym_wrappers.egg-info/SOURCES.txt
gym_wrappers.egg-info/dependency_links.txt
gym_wrappers.egg-info/requires.txt
gym_wrappers.egg-info/top_level.txt