Metadata-Version: 1.1
Name: gym-wrappers
Version: 0.1.0
Summary: Wrappers for common manipulations of Gym environments.
Home-page: http://github.com/danijar/gym-wrappers
Author: UNKNOWN
Author-email: UNKNOWN
License: Apache 2.0
Platform: UNKNOWN
Classifier: Programming Language :: Python :: 2
Classifier: Programming Language :: Python :: 3
Classifier: License :: OSI Approved :: Apache Software License
Classifier: Topic :: Scientific/Engineering :: Artificial Intelligence
Classifier: Intended Audience :: Science/Research
